interactive_process/__init__.py
interactive_process/interactive_process.py
interactive_process/poetry.toml
interactive_process/temp.py
interactive_process-0.2.5.dist-info/LICENSE
interactive_process-0.2.5.dist-info/METADATA
interactive_process-0.2.5.dist-info/WHEEL
interactive_process-0.2.5.dist-info/entry_points.txt
interactive_process-0.2.5.dist-info/RECORD
