Metadata-Version: 2.1
Name: interactive-process
Version: 0.2.5
Summary: 
Author: Yason Khaburzaniya
Author-email: yason@hey.com
Requires-Python: >=3.10,<4.0
Classifier: Programming Language :: Python :: 3
Classifier: Programming Language :: Python :: 3.10
Classifier: Programming Language :: Python :: 3.11
Classifier: Programming Language :: Python :: 3.12
Requires-Dist: ptyprocess (>=0.7.0,<0.8.0)
